LICENSE
MANIFEST.in
README.md
setup.py
assetfiles/__init__.py
assetfiles/assets.py
assetfiles/exceptions.py
assetfiles/handlers.py
assetfiles/models.py
assetfiles/settings.py
assetfiles/storage.py
assetfiles/urls.py
assetfiles/views.py
assetfiles/filters/__init__.py
assetfiles/filters/base.py
assetfiles/filters/coffee.py
assetfiles/filters/mixins.py
assetfiles/filters/sass.py
assetfiles/management/__init__.py
assetfiles/management/commands/__init__.py
assetfiles/management/commands/collectstatic.py
assetfiles/management/commands/findstatic.py
assetfiles/management/commands/runserver.py
assetfiles/scripts/sass_env.rb
assetfiles/scripts/sass_functions.rb
assetfiles/templatetags/__init__.py
assetfiles/templatetags/staticfiles.py
django_assetfiles.egg-info/PKG-INFO
django_assetfiles.egg-info/SOURCES.txt
django_assetfiles.egg-info/dependency_links.txt
django_assetfiles.egg-info/top_level.txt
tests/__init__.py
tests/base.py
tests/django_settings.py
tests/test_assets.py
tests/test_commands.py
tests/test_storage.py
tests/test_templatetags.py
tests/test_views.py
tests/urls.py
tests/filters/__init__.py
tests/filters/test_base.py
tests/filters/test_coffee.py
tests/filters/test_mixins.py
tests/filters/test_sass.py
tests/project-template/__init__.py
tests/project-template/app-1/__init__.py
tests/project-template/app-2/__init__.py
tests/project-template/templates/404.html