Metadata-Version: 1.1
Name: django-assetfiles
Version: 0.8.0
Summary: Drop-in replacement for staticfiles which handles asset processing.
Home-page: http://github.com/LocalMed/django-assetfiles
Author: LocalMed
Author-email: pete.browne@localmed.com
License: MIT
Platform: UNKNOWN
Classifier: Development Status :: 4 - Beta
Classifier: Environment :: Web Environment
Classifier: Framework :: Django
Classifier: Intended Audience :: Developers
Classifier: License :: OSI Approved :: MIT License
Classifier: Operating System :: OS Independent
Classifier: Programming Language :: Python
Classifier: Programming Language :: Python :: 2
Classifier: Programming Language :: Python :: 2.7
Classifier: Programming Language :: Python :: 3
Classifier: Programming Language :: Python :: 3.3
Classifier: Topic :: Internet :: WWW/HTTP
